odoo/addons/account_payment_batch_process/README.rst
odoo/addons/account_payment_batch_process/__init__.py
odoo/addons/account_payment_batch_process/__manifest__.py
odoo/addons/account_payment_batch_process/i18n/account_payment_batch_process.pot
odoo/addons/account_payment_batch_process/i18n/es.po
odoo/addons/account_payment_batch_process/i18n/it.po
odoo/addons/account_payment_batch_process/models/__init__.py
odoo/addons/account_payment_batch_process/models/payment_adjustment_reason.py
odoo/addons/account_payment_batch_process/readme/CONTRIBUTORS.rst
odoo/addons/account_payment_batch_process/readme/CREDITS.rst
odoo/addons/account_payment_batch_process/readme/DESCRIPTION.rst
odoo/addons/account_payment_batch_process/readme/HISTORY.rst
odoo/addons/account_payment_batch_process/security/ir.model.access.csv
odoo/addons/account_payment_batch_process/static/description/icon.png
odoo/addons/account_payment_batch_process/static/description/index.html
odoo/addons/account_payment_batch_process/views/account_move.xml
odoo/addons/account_payment_batch_process/views/account_payment.xml
odoo/addons/account_payment_batch_process/wizard/__init__.py
odoo/addons/account_payment_batch_process/wizard/account_payment_register.py
odoo/addons/account_payment_batch_process/wizard/account_payment_register.xml
odoo/addons/account_payment_batch_process/wizard/invoice_payment_line.py
odoo14_addon_account_payment_batch_process-14.0.1.2.0.dist-info/METADATA
odoo14_addon_account_payment_batch_process-14.0.1.2.0.dist-info/WHEEL
odoo14_addon_account_payment_batch_process-14.0.1.2.0.dist-info/top_level.txt
odoo14_addon_account_payment_batch_process-14.0.1.2.0.dist-info/RECORD
